cli/README.md
cli/__init__.py
cli/__main__.py
cli/app.py
cli/app.tcss
cli/utils.py
cli/widgets/__init__.py
cli/widgets/confirmation.py
cli/widgets/conversation.py
cli/widgets/loading.py
kader/__init__.py
kader/config.py
kader/agent/__init__.py
kader/agent/agents.py
kader/agent/base.py
kader/agent/logger.py
kader/memory/__init__.py
kader/memory/conversation.py
kader/memory/session.py
kader/memory/state.py
kader/memory/types.py
kader/prompts/__init__.py
kader/prompts/agent_prompts.py
kader/prompts/base.py
kader/prompts/templates/planning_agent.j2
kader/prompts/templates/react_agent.j2
kader/providers/__init__.py
kader/providers/base.py
kader/providers/mock.py
kader/providers/ollama.py
kader/tools/README.md
kader/tools/__init__.py
kader/tools/base.py
kader/tools/exec_commands.py
kader/tools/filesys.py
kader/tools/filesystem.py
kader/tools/protocol.py
kader/tools/rag.py
kader/tools/todo.py
kader/tools/utils.py
kader/tools/web.py
kader-0.1.6.dist-info/METADATA
kader-0.1.6.dist-info/WHEEL
kader-0.1.6.dist-info/entry_points.txt
kader-0.1.6.dist-info/RECORD
