Metadata-Version: 2.4
Name: kader
Version: 0.1.6
Summary: kader coding agent
Requires-Python: >=3.11
Requires-Dist: faiss-cpu>=1.9.0
Requires-Dist: jinja2>=3.1.6
Requires-Dist: loguru>=0.7.3
Requires-Dist: ollama>=0.6.1
Requires-Dist: outdated>=0.2.2
Requires-Dist: pyyaml>=6.0.3
Requires-Dist: tenacity>=9.1.2
Requires-Dist: textual[syntax]>=6.8.0
Requires-Dist: typing-extensions>=4.15.0
Requires-Dist: wcmatch>=10.1
